{"frameRate":24,"isGlobal":0,"armature":[{"skin":[{"name":"","slot":[{"display":[{"type":"image","name":"potion","transform":{}}],"name":"potion"},{"display":[{"type":"image","name":"potionGlow","transform":{"y":12}}],"name":"potionGlow"}]}],"slot":[{"name":"potion","parent":"potion","color":{}},{"z":1,"name":"potionGlow","parent":"glow","color":{}}],"type":"Armature","name":"Potion","ik":[],"bone":[{"name":"root","transform":{}},{"transform":{"y":-128},"name":"potion","parent":"root"},{"transform":{"y":-9.45,"x":3},"name":"glow","parent":"potion"}],"animation":[{"frame":[],"slot":[{"frame":[{"tweenEasing":null,"duration":60,"color":{}}],"name":"potion"},{"frame":[{"tweenEasing":null,"duration":60,"color":{}}],"name":"potionGlow"}],"duration":60,"bone":[{"frame":[{"tweenEasing":null,"transform":{},"duration":60}],"name":"root"},{"frame":[{"tweenEasing":0,"transform":{},"duration":16},{"tweenEasing":0,"transform":{"y":-18},"duration":16},{"tweenEasing":0,"transform":{"y":18},"duration":16},{"tweenEasing":0,"transform":{"y":15},"duration":12},{"tweenEasing":null,"transform":{},"duration":0}],"name":"potion"},{"frame":[{"tweenEasing":0,"transform":{},"duration":10},{"tweenEasing":0,"transform":{"y":-1,"skY":60.2826,"skX":60.2826,"x":16},"duration":14},{"tweenEasing":0,"transform":{"y":22,"skY":128.9032,"skX":128.9032,"x":16},"duration":18},{"tweenEasing":0,"transform":{"y":20.5333,"skY":-128.6356,"skX":-128.6356,"x":-18.7667},"duration":18},{"tweenEasing":null,"transform":{},"duration":0}],"name":"glow"}],"playTimes":0,"ffd":[],"name":"idle"}],"aabb":{"width":259,"y":-256.00000000000006,"height":258.55,"x":-128},"frameRate":24,"defaultActions":[{"gotoAndPlay":"idle"}]}],"name":"Potion","version":"4.0"}